django_advanced_password_validation/__init__.py
django_advanced_password_validation/advanced_password_validation.py
django_advanced_password_validation/tests/__init__.py
django_advanced_password_validation/tests/settings.py
django_advanced_password_validation/tests/test_validators.py
django_advanced_password_validation-1.2.0.dist-info/LICENSE.txt
django_advanced_password_validation-1.2.0.dist-info/METADATA
django_advanced_password_validation-1.2.0.dist-info/WHEEL
django_advanced_password_validation-1.2.0.dist-info/top_level.txt
django_advanced_password_validation-1.2.0.dist-info/RECORD
