Metadata-Version: 2.1
Name: django_advanced_password_validation
Version: 1.2.0
Summary: Extends Django password validation options in an attempt to keep up with industry standards for strong user passwords.
Author-email: Ezra Rice <ezra.j.rice@gmail.com>
License: Copyright 2020 Ezra Jacob Rice
Project-URL: repository, https://github.com/ezrajrice/django_advanced_password_validation
Keywords: django,password,validator
Classifier: Environment :: Web Environment
Classifier: Framework :: Django
Classifier: Intended Audience :: Developers
Classifier: License :: OSI Approved :: MIT License
Classifier: Operating System :: OS Independent
Classifier: Programming Language :: Python
Classifier: Programming Language :: Python :: 3
Classifier: Programming Language :: Python :: 3.12
Classifier: Topic :: Internet :: WWW/HTTP
Classifier: Topic :: Internet :: WWW/HTTP :: Dynamic Content
License-File: LICENSE.txt
